jupiterone/__init__.py
jupiterone/client.py
jupiterone/constants.py
jupiterone/errors.py
jupiterone-2.1.0.dist-info/licenses/LICENSE
jupiterone-2.1.0.dist-info/METADATA
jupiterone-2.1.0.dist-info/WHEEL
jupiterone-2.1.0.dist-info/top_level.txt
jupiterone-2.1.0.dist-info/RECORD
