Metadata-Version: 2.4
Name: jupiterone
Version: 2.1.0
Summary: A Python client for the JupiterOne API
Home-page: https://github.com/JupiterOne/jupiterone-api-client-python
Author: JupiterOne
Author-email: solutions@jupiterone.com
Maintainer: JupiterOne
License: MIT License
Classifier: Development Status :: 4 - Beta
Classifier: Intended Audience :: Developers
Classifier: Intended Audience :: Information Technology
Classifier: Intended Audience :: System Administrators
Classifier: License :: OSI Approved :: MIT License
Classifier: Natural Language :: English
Classifier: Operating System :: POSIX :: Linux
Classifier: Programming Language :: Python
Classifier: Topic :: Security
License-File: LICENSE
Requires-Dist: requests
Requires-Dist: retrying
Dynamic: author
Dynamic: author-email
Dynamic: classifier
Dynamic: home-page
Dynamic: license
Dynamic: license-file
Dynamic: maintainer
Dynamic: requires-dist
Dynamic: summary
